README.rst
setup.py
ethiopian_date/__init__.py
ethiopian_date/ethiopian_date.py
ethiopian_date/tests.py
ethiopian_date_converter.egg-info/PKG-INFO
ethiopian_date_converter.egg-info/SOURCES.txt
ethiopian_date_converter.egg-info/dependency_links.txt
ethiopian_date_converter.egg-info/requires.txt
ethiopian_date_converter.egg-info/top_level.txt